{
	"whenPaid":
	{	"Transaction":"date"
	},
	"whoSentEmail":
	{	"Email":"from"
	},
	"whoReceivedEmail":
	{	"Email":"to"
	},
	"whoWasCCed":
	{	"Email":"cc"
	},
	"whoWasBCCed":
	{	"Email":"bcc"
	},
	"whatAbout":
	{	"Email":"subject"
	},
	"whenWasSent":
	{	"Email":"date"
	},
	"whoPaid":
	{	"Transaction": "payer"
	},
	"wherePaymentOccured":
	{	"Transaction": "merchant_name"
	},
	"whenPaid":
	{	"Transaction": "date"
	},
	"whatWasPaymentAbout":
	{	"Transaction": "description"
	},
	"howWasPaid":
	{	"Transaction": "payment_method"
	},
	"whoMadeTheReservation":{
		"Email": "from"
	},
	"whenWasTheReservationMade":{
		 "Email":"date"
	},
	"whoIsTheOrganizer":{
		"Event": "organizer_id"
	},
	"whoIsTheEventCreator":{
		"Event": "creator_id"
	},
	"whenTheEventStarts":{
		"Event":"startTime"
	},
	"whenTheEventEnds":{
		"Event":"endTime"
	},
	"whenWasTheEventCreated":{
		"Event":"dateCreated"
	},
	"whatEvent":{
		"Event":"description"
	},
	"whoInitiatedTheConversation":{
		"Email":"from"
	}
}